pandioml/__init__.py
pandioml/requirements.txt
pandioml/core/__init__.py
pandioml/core/artifacts.py
pandioml/core/interact.py
pandioml/core/pipelines.py
pandioml/core/storage.py
pandioml/data/__init__.py
pandioml/data/agrawal.py
pandioml/data/credit_card_transactions.py
pandioml/data/form_submissions.py
pandioml/data/hosting.py
pandioml/data/led_generator.py
pandioml/data/movie_ratings.py
pandioml/data/people.py
pandioml/data/phishing_dataset.py
pandioml/data/record.py
pandioml/data/restaurant_visitors.py
pandioml/data/scikit_multiflow_classes.py
pandioml/data/sine_generator.py
pandioml/data/stream.py
pandioml/function/__init__.py
pandioml/function/base.py
pandioml/function/function.py
pandioml/metrics/__init__.py
pandioml/model/__init__.py
pandioml/model/anomaly_detection.py
pandioml/model/cluster.py
pandioml/model/ensemble.py
pandioml/model/evaluation.py
pandioml/model/expert.py
pandioml/model/factor.py
pandioml/model/feature_extraction.py
pandioml/model/feature_selection.py
pandioml/model/imblearn.py
pandioml/model/linear.py
pandioml/model/meta.py
pandioml/model/multiclass.py
pandioml/model/multioutput.py
pandioml/model/naive_bayes.py
pandioml/model/neighbors.py
pandioml/model/neural_network.py
pandioml/model/optim.py
pandioml/model/preprocessing.py
pandioml/model/proba.py
pandioml/model/reco.py
pandioml/model/stream.py
pandioml/model/time_series.py
pandioml/model/trees.py
pandioml/model/utility.py
pandioml/stats/__init__.py
pandioml-1.0.13.dist-info/LICENSE
pandioml-1.0.13.dist-info/METADATA
pandioml-1.0.13.dist-info/WHEEL
pandioml-1.0.13.dist-info/top_level.txt
pandioml-1.0.13.dist-info/RECORD
