Metadata-Version: 2.1
Name: pandioml
Version: 1.0.13
Summary: Pandio's machine learning library.
Home-page: https://github.com/pandio-com/pandioml
Author: Joshua Odmark
Author-email: josh@pandio.com
License: UNKNOWN
Keywords: machine learning data science pandio artificial intelligence build models online machine learning streaming classifiers supervised learning regressions
Platform: UNKNOWN
Classifier: Programming Language :: Python :: 3
Classifier: Operating System :: OS Independent
Classifier: Topic :: Documentation
Classifier: Development Status :: 5 - Production/Stable
Classifier: Intended Audience :: Developers
Classifier: Programming Language :: Python :: 3 :: Only
Classifier: Topic :: Software Development :: Libraries :: Python Modules
License-File: LICENSE
Requires-Dist: numpy (==1.20.1)
Requires-Dist: Faker (==8.1.1)
Requires-Dist: river (==0.7.0)
Requires-Dist: scikit-learn (==0.24.1)
Requires-Dist: pandiocli (==1.0.17)
Requires-Dist: six (==1.16.0)
Provides-Extra: pulsar
Requires-Dist: pulsar-client (==2.7.2) ; extra == 'pulsar'
